Workbook
Name monthly_price: Assumptions!$B$4
Name annual_price: Assumptions!$B$5
Name monthly_mix: Assumptions!$B$6
Name annual_mix: Assumptions!$B$7
Name starting_customers: Assumptions!$B$10
Name new_customers_monthly: Assumptions!$B$11
Name churn_rate: Assumptions!$B$12
Name cac: Assumptions!$B$13
Name cogs_per_customer: Assumptions!$B$16
Name sm_percent: Assumptions!$B$17
Name opex_fixed: Assumptions!$B$18

Sheet Assumptions
A1: SaaS Financial Model - Assumptions
A3: Pricing Assumptions
A4: Monthly Subscription Price | B4: 50
A5: Annual Subscription Price | B5: 500
A6: Monthly/Annual Mix - Monthly % | B6: 0.7
A7: Monthly/Annual Mix - Annual % | B7: 0.3
A9: Customer Assumptions
A10: Starting Customers | B10: 100
A11: Monthly New Customer Acquisition | B11: 50
A12: Monthly Churn Rate | B12: 0.05
A13: Customer Acquisition Cost (CAC) | B13: 200
A15: Cost Assumptions
A16: COGS per Customer per Month | B16: 10
A17: Sales & Marketing % of Revenue | B17: 0.4
A18: Fixed Operating Expenses (Monthly) | B18: 50000

Sheet Financial Model
A1: Month | B1: 0 | C1: 1 | D1: 2 | E1: 3 | F1: 4 | G1: 5 | H1: 6 | I1: 7 | J1: 8 | K1: 9 | L1: 10 | M1: 11 | N1: 12 | O1: 13 | P1: 14 | Q1: 15 | R1: 16 | S1: 17 | T1: 18 | U1: 19 | V1: 20 | W1: 21 | X1: 22 | Y1: 23 | Z1: 24 | AA1: 25 | AB1: 26 | AC1: 27 | AD1: 28 | AE1: 29 | AF1: 30 | AG1: 31 | AH1: 32 | AI1: 33 | AJ1: 34 | AK1: 35 | AL1: 36
A3: CUSTOMER METRICS
A4: Beginning Customers | B4: =starting_customers | C4: =B7 | D4: =C7 | E4: =D7 | F4: =E7 | G4: =F7 | H4: =G7 | I4: =H7 | J4: =I7 | ... AL4: =AK7
A5: New Customers | B5: =new_customers_monthly | C5: =new_customers_monthly | D5: =new_customers_monthly | E5: =new_customers_monthly | F5: =new_customers_monthly | G5: =new_customers_monthly | H5: =new_customers_monthly | I5: =new_customers_monthly | ... AL5: =new_customers_monthly
A6: Churned Customers | B6: =B4*churn_rate | C6: =C4*churn_rate | D6: =D4*churn_rate | E6: =E4*churn_rate | F6: =F4*churn_rate | G6: =G4*churn_rate | H6: =H4*churn_rate | I6: =I4*churn_rate | ... AL6: =AL4*churn_rate
A7: Ending Customers | B7: =B4+B5-B6 | C7: =C4+C5-C6 | D7: =D4+D5-D6 | E7: =E4+E5-E6 | F7: =F4+F5-F6 | G7: =G4+G5-G6 | H7: =H4+H5-H6 | I7: =I4+I5-I6 | ... AL7: =AL4+AL5-AL6
A9: REVENUE
A10: Monthly Subscription Customers | B10: =B7*monthly_mix | C10: =C7*monthly_mix | D10: =D7*monthly_mix | E10: =E7*monthly_mix | F10: =F7*monthly_mix | G10: =G7*monthly_mix | H10: =H7*monthly_mix | I10: =I7*monthly_mix | ... AL10: =AL7*monthly_mix
A11: Annual Subscription Customers | B11: =B7*annual_mix | C11: =C7*annual_mix | D11: =D7*annual_mix | E11: =E7*annual_mix | F11: =F7*annual_mix | G11: =G7*annual_mix | H11: =H7*annual_mix | I11: =I7*annual_mix | ... AL11: =AL7*annual_mix
A12: MRR (Monthly Subs) | B12: =B10*monthly_price | C12: =C10*monthly_price | D12: =D10*monthly_price | E12: =E10*monthly_price | F12: =F10*monthly_price | G12: =G10*monthly_price | H12: =H10*monthly_price | I12: =I10*monthly_price | ... AL12: =AL10*monthly_price
A13: ARR Recognition (Monthly) | B13: =B11*annual_price/12 | C13: =C11*annual_price/12 | D13: =D11*annual_price/12 | E13: =E11*annual_price/12 | F13: =F11*annual_price/12 | G13: =G11*annual_price/12 | H13: =H11*annual_price/12 | I13: =I11*annual_price/12 | ... AL13: =AL11*annual_price/12
A14: Total Monthly Revenue | B14: =B12+B13 | C14: =C12+C13 | D14: =D12+D13 | E14: =E12+E13 | F14: =F12+F13 | G14: =G12+G13 | H14: =H12+H13 | I14: =I12+I13 | ... AL14: =AL12+AL13
A15: ARR (Annual Run Rate) | B15: =B14*12 | C15: =C14*12 | D15: =D14*12 | E15: =E14*12 | F15: =F14*12 | G15: =G14*12 | H15: =H14*12 | I15: =I14*12 | ... AL15: =AL14*12
A17: EXPENSES
A18: CAC Costs | B18: =B5*cac | C18: =C5*cac | D18: =D5*cac | E18: =E5*cac | F18: =F5*cac | G18: =G5*cac | H18: =H5*cac | I18: =I5*cac | ... AL18: =AL5*cac
A19: COGS | B19: =B7*cogs_per_customer | C19: =C7*cogs_per_customer | D19: =D7*cogs_per_customer | E19: =E7*cogs_per_customer | F19: =F7*cogs_per_customer | G19: =G7*cogs_per_customer | H19: =H7*cogs_per_customer | I19: =I7*cogs_per_customer | ... AL19: =AL7*cogs_per_customer
A20: Sales & Marketing | B20: =B14*sm_percent | C20: =C14*sm_percent | D20: =D14*sm_percent | E20: =E14*sm_percent | F20: =F14*sm_percent | G20: =G14*sm_percent | H20: =H14*sm_percent | I20: =I14*sm_percent | ... AL20: =AL14*sm_percent
A21: Operating Expenses | B21: =opex_fixed | C21: =opex_fixed | D21: =opex_fixed | E21: =opex_fixed | F21: =opex_fixed | G21: =opex_fixed | H21: =opex_fixed | I21: =opex_fixed | ... AL21: =opex_fixed
A22: Total Expenses | B22: =SUM(B18:B21) | C22: =SUM(C18:C21) | D22: =SUM(D18:D21) | E22: =SUM(E18:E21) | F22: =SUM(F18:F21) | G22: =SUM(G18:G21) | H22: =SUM(H18:H21) | I22: =SUM(I18:I21) | ... AL22: =SUM(AL18:AL21)
A24: PROFITABILITY
A25: Gross Profit | B25: =B14-B19 | C25: =C14-C19 | D25: =D14-D19 | E25: =E14-E19 | F25: =F14-F19 | G25: =G14-G19 | H25: =H14-H19 | I25: =I14-I19 | ... AL25: =AL14-AL19
A26: Gross Margin % | B26: =IF(B14=0,0,B25/B14) | C26: =IF(C14=0,0,C25/C14) | D26: =IF(D14=0,0,D25/D14) | E26: =IF(E14=0,0,E25/E14) | F26: =IF(F14=0,0,F25/F14) | G26: =IF(G14=0,0,G25/G14) | H26: =IF(H14=0,0,H25/H14) | I26: =IF(I14=0,0,I25/I14) | ... AL26: =IF(AL14=0,0,AL25/AL14)
A27: Operating Profit | B27: =B14-B22 | C27: =C14-C22 | D27: =D14-D22 | E27: =E14-E22 | F27: =F14-F22 | G27: =G14-G22 | H27: =H14-H22 | I27: =I14-I22 | ... AL27: =AL14-AL22
A28: Operating Margin % | B28: =IF(B14=0,0,B27/B14) | C28: =IF(C14=0,0,C27/C14) | D28: =IF(D14=0,0,D27/D14) | E28: =IF(E14=0,0,E27/E14) | F28: =IF(F14=0,0,F27/F14) | G28: =IF(G14=0,0,G27/G14) | H28: =IF(H14=0,0,H27/H14) | I28: =IF(I14=0,0,I27/I14) | ... AL28: =IF(AL14=0,0,AL27/AL14)
A29: Monthly Cash Flow | B29: =B27 | C29: =C27 | D29: =D27 | E29: =E27 | F29: =F27 | G29: =G27 | H29: =H27 | I29: =I27 | ... AL29: =AL27
A30: Cumulative Cash Flow | B30: =B29 | C30: =B30+C29 | D30: =C30+D29 | E30: =D30+E29 | F30: =E30+F29 | G30: =F30+G29 | H30: =G30+H29 | I30: =H30+I29 | J30: =I30+J29 | ... AL30: =AK30+AL29
A32: KEY METRICS
A33: Customer Lifetime Value (LTV) | B33: =(monthly_price*monthly_mix + annual_price/12*annual_mix)/churn_rate | C33: =(monthly_price*monthly_mix + annual_price/12*annual_mix)/churn_rate | D33: =(monthly_price*monthly_mix + annual_price/12*annual_mix)/churn_rate | E33: =(monthly_price*monthly_mix + annual_price/12*annual_mix)/churn_rate | F33: =(monthly_price*monthly_mix + annual_price/12*annual_mix)/churn_rate | G33: =(monthly_price*monthly_mix + annual_price/12*annual_mix)/churn_rate | H33: =(monthly_price*monthly_mix + annual_price/12*annual_mix)/churn_rate | I33: =(monthly_price*monthly_mix + annual_price/12*annual_mix)/churn_rate | ... AL33: =(monthly_price*monthly_mix + annual_price/12*annual_mix)/churn_rate
A34: LTV:CAC Ratio | B34: =B33/cac | C34: =C33/cac | D34: =D33/cac | E34: =E33/cac | F34: =F33/cac | G34: =G33/cac | H34: =H33/cac | I34: =I33/cac | ... AL34: =AL33/cac

Sheet Dashboard
A1: SaaS Financial Model Dashboard
A3: KEY MILESTONES
A4: Metric | B4: Month 12 | C4: Month 24 | D4: Month 36
A5: Total Customers | B5: ='Financial Model'!G7 | C5: ='Financial Model'!Q7 | D5: ='Financial Model'!AK7
A6: Monthly Revenue | B6: ='Financial Model'!G14 | C6: ='Financial Model'!Q14 | D6: ='Financial Model'!AK14
A7: ARR | B7: ='Financial Model'!G15 | C7: ='Financial Model'!Q15 | D7: ='Financial Model'!AK15
A8: Gross Margin % | B8: ='Financial Model'!G26 | C8: ='Financial Model'!Q26 | D8: ='Financial Model'!AK26
A9: Operating Margin % | B9: ='Financial Model'!G28 | C9: ='Financial Model'!Q28 | D9: ='Financial Model'!AK28
A10: LTV:CAC Ratio | B10: ='Financial Model'!G34 | C10: ='Financial Model'!Q34 | D10: ='Financial Model'!AK34
A11: Cumulative Cash Flow | B11: ='Financial Model'!G30 | C11: ='Financial Model'!Q30 | D11: ='Financial Model'!AK30
A14: BUSINESS HEALTH INDICATORS
A15: Average Gross Margin (36 months) | B15: =AVERAGE('Financial Model'!B26:AK26)
A16: Average LTV:CAC Ratio (36 months) | B16: =AVERAGE('Financial Model'!B34:AK34)
A17: Months to Profitability | B17: =IFERROR(MATCH(TRUE,'Financial Model'!B29:AK29>0,0),"Not Yet")
A18: Months to Positive Cumulative Cash Flow | B18: =IFERROR(MATCH(TRUE,'Financial Model'!B30:AK30>0,0),"Not Yet")
